{
  "latest_sync_time": "2026-06-13T06:28:57.744938+00:00",
  "status": "success",
  "connectors": {
    "run": [
      "benchmark",
      "model",
      "prompt",
      "dataset",
      "tool",
      "news",
      "indexes_legacy",
      "entity_indexer",
      "search_index",
      "analytics",
      "docs",
      "graph_exporter",
      "exporters",
      "report_legacy",
      "dashboard",
      "plugins",
      "manifests",
      "graph_api",
      "integrity_checker",
      "snapshot_generator",
      "release_builder"
    ],
    "failed": []
  },
  "entity_counts": 1230,
  "cache_statistics": {
    "hits": 9,
    "misses": 0
  },
  "warning_count": 0,
  "error_count": 0
}